findercore/__init__.py
findercore/finder.py
FinderCore-0.1.dist-info/METADATA
FinderCore-0.1.dist-info/WHEEL
FinderCore-0.1.dist-info/top_level.txt
FinderCore-0.1.dist-info/RECORD
