Metadata-Version: 2.1
Name: FinderCore
Version: 0.1
Summary: FinderCore - Librería para buscar usuarios de minecraft en nuestras base de datos
Home-page: https://core-hub-node.vercel.app/finder
Author: Saind_YTx
Author-email: devsaindytx@gmail.com
License: UNKNOWN
Platform: UNKNOWN
Classifier: Programming Language :: Python :: 3
Classifier: License :: OSI Approved :: MIT License
Requires-Python: >=3.6
Requires-Dist: requests
